duffel_api/__init__.py
duffel_api/client.py
duffel_api/http_client.py
duffel_api/utils.py
duffel_api/api/__init__.py
duffel_api/api/booking/__init__.py
duffel_api/api/booking/offer_requests.py
duffel_api/api/booking/offers.py
duffel_api/api/booking/order_cancellations.py
duffel_api/api/booking/order_change_offers.py
duffel_api/api/booking/order_change_requests.py
duffel_api/api/booking/order_changes.py
duffel_api/api/booking/orders.py
duffel_api/api/booking/partial_offer_requests.py
duffel_api/api/booking/payments.py
duffel_api/api/booking/seat_maps.py
duffel_api/api/duffel_payments/__init__.py
duffel_api/api/duffel_payments/payment_intents.py
duffel_api/api/links/__init__.py
duffel_api/api/links/sessions.py
duffel_api/api/notifications/__init__.py
duffel_api/api/notifications/webhooks.py
duffel_api/api/supporting/__init__.py
duffel_api/api/supporting/aircraft.py
duffel_api/api/supporting/airlines.py
duffel_api/api/supporting/airports.py
duffel_api/models/__init__.py
duffel_api/models/aircraft.py
duffel_api/models/airline.py
duffel_api/models/airport.py
duffel_api/models/loyalty_programme_account.py
duffel_api/models/offer.py
duffel_api/models/offer_request.py
duffel_api/models/order.py
duffel_api/models/order_cancellation.py
duffel_api/models/order_change.py
duffel_api/models/order_change_offer.py
duffel_api/models/order_change_request.py
duffel_api/models/payment.py
duffel_api/models/payment_intent.py
duffel_api/models/seat_map.py
duffel_api/models/session.py
duffel_api/models/webhook.py
tests/__init__.py
tests/fixtures.py
tests/test_aircraft.py
tests/test_aircrafts.py
tests/test_airline.py
tests/test_airlines.py
tests/test_airport.py
tests/test_airports.py
tests/test_http_client.py
tests/test_links_sessions.py
tests/test_loyalty_programme_account.py
tests/test_offer.py
tests/test_offer_request.py
tests/test_offer_requests.py
tests/test_offers.py
tests/test_order.py
tests/test_order_cancellation.py
tests/test_order_cancellations.py
tests/test_order_change.py
duffel_api-0.6.2.dist-info/LICENSE
duffel_api-0.6.2.dist-info/METADATA
duffel_api-0.6.2.dist-info/WHEEL
duffel_api-0.6.2.dist-info/top_level.txt
duffel_api-0.6.2.dist-info/RECORD
