Metadata-Version: 2.1
Name: duffel-api
Version: 0.6.2
Summary: Client library for the Duffel API
Home-page: https://github.com/duffelhq/duffel-api-python
Author: Duffel Engineering
Author-email: client-libraries@duffel.com
License: MIT
Keywords: duffel api flights airports airlines aircraft
Classifier: Development Status :: 3 - Alpha
Classifier: Programming Language :: Python :: 3
Classifier: License :: OSI Approved :: MIT License
Classifier: Intended Audience :: Developers
Requires-Python: >=3.8
License-File: LICENSE
Requires-Dist: requests >=2.25
